{
  "name": "Angulotls",
  "malice": [
    {
      "type": "feature",
      "feature_type": "trait",
      "name": "Leapfrog",
      "icon": "⭐️",
      "cost": "3",
      "effects": [
        {
          "effect": "Until the end of the round, when an angulotl moves through an inactive angulotl's space, the inactive angulotl can use a free triggered action to jump 3 squares."
        }
      ]
    },
    {
      "type": "feature",
      "feature_type": "trait",
      "name": "Resonating Croak",
      "icon": "❇️",
      "cost": "5",
      "effects": [
        {
          "tier1": "5 sonic damage; slowed (EoT)",
          "tier2": "4 sonic damage",
          "tier3": "No effect.",
          "effect": "Each angulotl in the encounter puffs out their throat and starts loudly droning. Any non-angulotl adjacent to an angulotl makes an **Intuition test.**"
        }
      ]
    },
    {
      "type": "feature",
      "feature_type": "trait",
      "name": "Rainfall",
      "icon": "🌀",
      "cost": "7",
      "effects": [
        {
          "effect": "An angulotl calls clouds to cover the encounter map and unleash rain until the end of the round. Any creature or object that is exposed to the sky is wet until the end of the encounter."
        }
      ]
    }
  ],
  "monsters": [
    {
      "name": "Angulotl Cleaver",
      "level": 1,
      "roles": [
        "Minion Ambusher"
      ],
      "ancestry": [
        "Angulotl",
        "Humanoid"
      ],
      "ev": 3,
      "stamina": 4,
      "speed": 6,
      "movement": "Climb, swim",
      "size": "1S",
      "stability": 0,
      "free_strike": 2,
      "with_captain": "+1 damage bonus to strikes",
      "might": 0,
      "agility": 2,
      "reason": 0,
      "intuition": 1,
      "presence": 0,
      "immunities": [
        "Poison 2"
      ],
      "features": [
        {
          "type": "feature",
          "feature_type": "ability",
          "name": "Hop and Chop",
          "icon": "🗡",
          "ability_type": "Signature Ability",
          "keywords": [
            "Melee",
            "Strike",
            "Weapon"
          ],
          "usage": "Main action",
          "distance": "Melee 1",
          "target": "One creature or object per minion",
          "effects": [
            {
              "roll": 2,
              "tier1": "2 damage",
              "tier2": "4 damage",
              "tier3": "5 damage"
            },
            {
              "name": "Effect",
              "effect": "The cleaver jumps up to 4 squares before or after making this strike."
            }
          ]
        },
        {
          "type": "feature",
          "feature_type": "trait",
          "name": "Toxiferous",
          "icon": "⭐️",
          "effects": [
            {
              "effect": "Whenever an adjacent enemy grabs the cleaver or uses a melee ability against them, that enemy takes 1 poison damage."
            }
          ]
        }
      ]
    },
    {
      "name": "Angulotl Dart",
      "level": 1,
      "roles": [
        "Minion Artillery"
      ],
      "ancestry": [
        "Angulotl",
        "Humanoid"
      ],
      "ev": 3,
      "stamina": 3,
      "speed": 5,
      "movement": "Climb, swim",
      "size": "1S",
      "stability": 0,
      "free_strike": 2,
      "with_captain": "+4 bonus to ranged distance",
      "might": 0,
      "agility": 2,
      "reason": 1,
      "intuition": 0,
      "presence": 0,
      "immunities": [
        "Poison 2"
      ],
      "features": [
        {
          "type": "feature",
          "feature_type": "ability",
          "name": "Poison Dart",
          "icon": "🏹",
          "ability_type": "Signature Ability",
          "keywords": [
            "Ranged",
            "Strike",
            "Weapon"
          ],
          "usage": "Main action",
          "distance": "Ranged 8",
          "target": "One creature per minion",
          "effects": [
            {
              "roll": 2,
              "tier1": "2 poison damage",
              "tier2": "4 poison damage",
              "tier3": "5 poison damage"
            },
            {
              "name": "Effect",
              "effect": "The dart gains an edge on this ability against any target who has less than full Stamina."
            }
          ]
        },
        {
          "type": "feature",
          "feature_type": "trait",
          "name": "Toxiferous",
          "icon": "⭐️",
          "effects": [
            {
              "effect": "Whenever an adjacent enemy grabs the dart or uses a melee ability against them, that enemy takes 1 poison damage."
            }
          ]
        }
      ]
    },
    {
      "name": "Angulotl Daybringer",
      "level": 1,
      "roles": [
        "Leader"
      ],
      "ancestry": [
        "Angulotl",
        "Humanoid"
      ],
      "ev": 12,
      "stamina": 80,
      "speed": 5,
      "movement": "Climb, swim",
      "size": "1M",
      "stability": 1,
      "free_strike": 4,
      "might": 3,
      "agility": 2,
      "reason": 0,
      "intuition": 2,
      "presence": 0,
      "immunities": [
        "Poison 3"
      ],
      "features": [
        {
          "type": "feature",
          "feature_type": "ability",
          "name": "Acid Grasp",
          "icon": "🗡",
          "ability_type": "Signature Ability",
          "keywords": [
            "Melee",
            "Strike",
            "Weapon"
          ],
          "usage": "Main action",
          "distance": "Melee 1",
          "target": "Two creatures or objects",
          "effects": [
            {
              "roll": 3,
              "tier1": "7 acid damage; A < 1 dazed (save ends)",
              "tier2": "10 acid damage; A < 2 dazed (save ends)",
              "tier3": "13 acid damage; A < 3 dazed (save ends)"
            },
            {
              "name": "Effect",
              "effect": "The next time the target makes a strike against the daybringer, the target takes 4 acid damage after the strike is resolved."
            },
            {
              "effect": "The daybringer jumps up to 3 squares before or after using this ability.",
              "cost": "1"
            }
          ]
        },
        {
          "type": "feature",
          "feature_type": "ability",
          "name": "Sun Lamp",
          "icon": "👤",
          "keywords": [
            "-"
          ],
          "usage": "Maneuver",
          "distance": "Self",
          "target": "Self",
          "effects": [
            {
              "name": "Effect",
              "effect": "The daybringer expands their throat to make it resemble the sun until the start of their next turn. During that time, each angulotl who starts their turn within 10 squares of the daybringer regains 5 Stamina and gains a +3 bonus to speed until the end of their turn."
            }
          ]
        },
        {
          "type": "feature",
          "feature_type": "ability",
          "name": "Tongue Slap",
          "icon": "❗️",
          "keywords": [
            "Melee"
          ],
          "usage": "Triggered action",
          "distance": "Melee 5",
          "target": "One creature",
          "trigger": "The target makes a strike against the daybringer or an ally that isn't a critical hit.",
          "effects": [
            {
              "name": "Effect",
              "effect": "The outcome of the strike's power roll is reduced by one tier."
            },
            {
              "effect": "The target is pulled up to 4 squares after the strike resolves.",
              "cost": "2"
            }
          ]
        },
        {
          "type": "feature",
          "feature_type": "trait",
          "name": "Moisturizing End Effect",
          "icon": "⭐️",
          "effects": [
            {
              "effect": "At the end of each of the daybringer's turns, they can either take 5 damage or end the wet effect on an adjacent creature in order to end one effect on them that can be ended by a saving throw. This damage can't be reduced in any way."
            }
          ]
        },
        {
          "type": "feature",
          "feature_type": "ability",
          "name": "New Dawn",
          "icon": "☠️",
          "ability_type": "Villain Action 1",
          "keywords": [
            "Ranged"
          ],
          "usage": "-",
          "distance": "Ranged 10",
          "target": "Special",
          "effects": [
            {
              "name": "Effect",
              "effect": "Four **angulotl pollywogs** erupt from the daybringer's back and waddle into unoccupied spaces within distance."
            }
          ]
        },
        {
          "type": "feature",
          "feature_type": "ability",
          "name": "Plague of Frogs",
          "icon": "☠️",
          "ability_type": "Villain Action 2",
          "keywords": [
            "Area"
          ],
          "usage": "-",
          "distance": "8 burst",
          "target": "Self and each ally in the area",
          "effects": [
            {
              "name": "Effect",
              "effect": "Each target can jump up to 4 squares. Each non-minion target can make a free strike at the end of the jump."
            }
          ]
        },
        {
          "type": "feature",
          "feature_type": "ability",
          "name": "It Is Day",
          "icon": "☠️",
          "ability_type": "Villain Action 3",
          "keywords": [
            "-"
          ],
          "usage": "-",
          "distance": "Special",
          "target": "Special",
          "effects": [
            {
              "name": "Effect",
              "effect": "The encounter map dries up and each enemy and object on it is illuminated until the end of the encounter. An illuminated creature or object can't hide or become invisible, and any strike made against an illuminated target gains an edge. Additionally, each enemy in the encounter who is wet has that effect end and takes 6 acid damage. Each angulotl in the encounter has a double edge on their next strike."
            }
          ]
        },
        {
          "type": "feature",
          "feature_type": "trait",
          "name": "Toxiferous",
          "icon": "⭐️",
          "effects": [
            {
              "effect": "Whenever an adjacent enemy grabs the daybringer or uses a melee ability against them, that enemy takes 3 poison damage."
            }
          ]
        }
      ]
    },
    {
      "name": "Angulotl Needler",
      "level": 1,
      "roles": [
        "Horde Artillery"
      ],
      "ancestry": [
        "Angulotl",
        "Humanoid"
      ],
      "ev": 3,
      "stamina": 10,
      "speed": 5,
      "movement": "Climb, swim",
      "size": "1S",
      "stability": 0,
      "free_strike": 2,
      "might": 0,
      "agility": 2,
      "reason": 1,
      "intuition": 0,
      "presence": -1,
      "immunities": [
        "Poison 2"
      ],
      "features": [
        {
          "type": "feature",
          "feature_type": "ability",
          "name": "Blowgun",
          "icon": "🏹",
          "ability_type": "Signature Ability",
          "keywords": [
            "Ranged",
            "Strike",
            "Weapon"
          ],
          "usage": "Main action",
          "distance": "Ranged 15",
          "target": "One creature",
          "effects": [
            {
              "roll": 2,
              "tier1": "4 poison damage",
              "tier2": "6 poison damage",
              "tier3": "7 poison damage"
            },
            {
              "effect": "A target who has M < 2 is weakened (save ends). A target weakened this way takes 2 poison damage at the start of each of their turns.",
              "cost": "2"
            }
          ]
        },
        {
          "type": "feature",
          "feature_type": "trait",
          "name": "Toxiferous",
          "icon": "⭐️",
          "effects": [
            {
              "effect": "Whenever an adjacent enemy grabs the needler or uses a melee ability against them, that enemy takes 2 poison damage."
            }
          ]
        }
      ]
    },
    {
      "name": "Angulotl Pollywog",
      "level": 1,
      "roles": [
        "Minion Harrier"
      ],
      "ancestry": [
        "Angulotl"
      ],
      "ev": 3,
      "stamina": 4,
      "speed": 6,
      "movement": "Climb, swim",
      "size": "1S",
      "stability": 0,
      "free_strike": 1,
      "with_captain": "+2 bonus to speed",
      "might": 0,
      "agility": 2,
      "reason": -2,
      "intuition": -2,
      "presence": 0,
      "immunities": [
        "Poison 2"
      ],
      "features": [
        {
          "type": "feature",
          "feature_type": "ability",
          "name": "Nip",
          "icon": "🗡",
          "ability_type": "Signature Ability",
          "keywords": [
            "Melee",
            "Strike",
            "Weapon"
          ],
          "usage": "Main action",
          "distance": "Melee 1",
          "target": "One creature per minion",
          "effects": [
            {
              "roll": 2,
              "tier1": "1 poison damage",
              "tier2": "2 poison damage; the pollywog can shift 1 square",
              "tier3": "3 poison damage; the pollywog shifts up to 3 squares"
            }
          ]
        },
        {
          "type": "feature",
          "feature_type": "trait",
          "name": "Quick Snack",
          "icon": "⭐️",
          "effects": [
            {
              "effect": "Any angulotl who can target the pollywog with a melee free strike can eat them as a maneuver. The angulotl regains 4 Stamina and is wet until the end of their next turn."
            }
          ]
        }
      ]
    },
    {
      "name": "Angulotl Slink",
      "level": 1,
      "roles": [
        "Horde Ambusher"
      ],
      "ancestry": [
        "Angulotl",
        "Humanoid"
      ],
      "ev": 3,
      "stamina": 15,
      "speed": 5,
      "movement": "Climb, swim",
      "size": "1S",
      "stability": 0,
      "free_strike": 2,
      "might": 1,
      "agility": 2,
      "reason": 0,
      "intuition": 0,
      "presence": 0,
      "immunities": [
        "Poison 2"
      ],
      "features": [
        {
          "type": "feature",
          "feature_type": "ability",
          "name": "Tonguelash",
          "icon": "🗡",
          "ability_type": "Signature Ability",
          "keywords": [
            "Melee",
            "Strike",
            "Weapon"
          ],
          "usage": "Main action",
          "distance": "Melee 6",
          "target": "One creature or object",
          "effects": [
            {
              "roll": 2,
              "tier1": "4 damage; pull 2",
              "tier2": "6 damage; pull 4",
              "tier3": "7 damage; pull 6"
            },
            {
              "name": "Effect",
              "effect": "The target is wet (save ends). Any ally targeted by this ability ignores the damage, is wet until the end of the encounter, and is pulled up to 6 squares, ignoring stability."
            }
          ]
        },
        {
          "type": "feature",
          "feature_type": "ability",
          "name": "Hop To It",
          "icon": "👤",
          "keywords": [
            "-"
          ],
          "usage": "Free maneuver",
          "distance": "Self",
          "target": "Self",
          "cost": "2",
          "effects": [
            {
              "name": "Effect",
              "effect": "The slink jumps up to 3 squares. If they have cover or concealment when they land, they can attempt to hide."
            }
          ]
        },
        {
          "type": "feature",
          "feature_type": "trait",
          "name": "Adhesive",
          "icon": "⭐️",
          "effects": [
            {
              "effect": "The slink excretes a sticky residue into their square at the end of each of their turns. Any non-angulotl who enters or leaves the square is stuck, and must use a maneuver to break free or be restrained until the end of their turn. Objects are likewise affected, and a creature must use a maneuver to remove an object from the square."
            }
          ]
        },
        {
          "type": "feature",
          "feature_type": "trait",
          "name": "Toxiferous",
          "icon": "⭐️",
          "effects": [
            {
              "effect": "Whenever an adjacent enemy grabs the slink or uses a melee ability against them, that enemy takes 2 poison damage."
            }
          ]
        }
      ]
    },
    {
      "name": "Angulotl Wave",
      "level": 1,
      "roles": [
        "Horde Controller"
      ],
      "ancestry": [
        "Angulotl",
        "Humanoid"
      ],
      "ev": 3,
      "stamina": 10,
      "speed": 5,
      "movement": "Climb, swim",
      "size": "1S",
      "stability": 0,
      "free_strike": 1,
      "might": 0,
      "agility": 0,
      "reason": 0,
      "intuition": 2,
      "presence": 2,
      "immunities": [
        "Poison 2"
      ],
      "features": [
        {
          "type": "feature",
          "feature_type": "ability",
          "name": "Refulgent Beams",
          "icon": "🏹",
          "ability_type": "Signature Ability",
          "keywords": [
            "Magic",
            "Ranged",
            "Strike"
          ],
          "usage": "Main action",
          "distance": "Ranged 8",
          "target": "Two creatures or objects",
          "effects": [
            {
              "roll": 2,
              "tier1": "3 holy damage",
              "tier2": "4 holy damage; R < 1 the target is illuminated (save ends)",
              "tier3": "5 holy damage; R < 2 the target is illuminated (save ends)"
            },
            {
              "name": "Effect",
              "effect": "An illuminated creature or object can't hide or become invisible, and any strike made against an illuminated target gains an edge."
            }
          ]
        },
        {
          "type": "feature",
          "feature_type": "ability",
          "name": "Noxious Bubble",
          "icon": "🔳",
          "keywords": [
            "Area",
            "Magic",
            "Ranged"
          ],
          "usage": "Main action",
          "distance": "2 cube of unoccupied space within 10",
          "target": "Special",
          "cost": "2",
          "effects": [
            {
              "tier1": "3 poison damage; the target is wet and weakened (save ends)",
              "tier2": "2 poison damage; the target is wet (save ends)",
              "tier3": "1 poison damage; the target is wet (EoT)",
              "name": "Effect",
              "effect": "A bubble of toxic gas fills the area, ready to pop. If any creature or object touches the bubble or if the bubble takes damage, it bursts. Each angulotl adjacent to the bubble is wet until the end of the encounter, and each enemy adjacent to the bubble makes a **Might test**."
            }
          ]
        },
        {
          "type": "feature",
          "feature_type": "trait",
          "name": "Toxiferous",
          "icon": "⭐️",
          "effects": [
            {
              "effect": "Whenever an adjacent enemy grabs the wave or uses a melee ability against them, that enemy takes 2 poison damage."
            }
          ]
        }
      ]
    },
    {
      "name": "Clawfish",
      "level": 1,
      "roles": [
        "Minion Brute"
      ],
      "ancestry": [
        "Angulotl",
        "Animal"
      ],
      "ev": 3,
      "stamina": 5,
      "speed": 5,
      "movement": "Climb, swim",
      "size": "1S",
      "stability": 0,
      "free_strike": 2,
      "with_captain": "Gain an edge on strikes",
      "might": 0,
      "agility": 2,
      "reason": -3,
      "intuition": -2,
      "presence": 1,
      "immunities": [
        "Lightning 3",
        "Poison 2"
      ],
      "features": [
        {
          "type": "feature",
          "feature_type": "ability",
          "name": "Hookclaw",
          "icon": "🗡",
          "ability_type": "Signature Ability",
          "keywords": [
            "Melee",
            "Strike",
            "Weapon"
          ],
          "usage": "Main action",
          "distance": "Melee 1",
          "target": "One creature or object per minion",
          "effects": [
            {
              "roll": 2,
              "tier1": "2 damage",
              "tier2": "4 damage",
              "tier3": "5 damage; grabbed"
            },
            {
              "name": "Effect",
              "effect": "Any target grabbed this way takes 2 lightning damage at the start of each of their turns."
            }
          ]
        },
        {
          "type": "feature",
          "feature_type": "trait",
          "name": "Shocking",
          "icon": "⭐️",
          "effects": [
            {
              "effect": "At the start of each of their turns, the clawfish deals 2 lightning damage to each wet enemy within 2 squares."
            }
          ]
        }
      ]
    }
  ]
}
